{"kind":"identitytoolkit#DownloadAccountResponse","users":[{"localId":"mJBbyK6AUMUMSvsuj337jBPeo9fz","createdAt":"1611428730066","lastLoginAt":"1611428730065","emailVerified":false,"email":"lukeingalls@me.com","salt":"fakeSaltKoHJWxPS0akPjOOf9fVb","passwordHash":"fakeHash:salt=fakeSaltKoHJWxPS0akPjOOf9fVb:password=jcCMNH6D7ATyFAf","passwordUpdatedAt":1611428730066,"validSince":"1611428730","providerUserInfo":[{"providerId":"password","email":"lukeingalls@me.com","federatedId":"lukeingalls@me.com","rawId":"lukeingalls@me.com"}]}]}